deployml/__init__.py
deployml/api.py
deployml/cli/__init__.py
deployml/cli/cli.py
deployml/diagnostics/__init__.py
deployml/diagnostics/doctor.py
deployml/enum/__init__.py
deployml/enum/cloud_provider.py
deployml/enum/deployment_type.py
deployml/notebook/__init__.py
deployml/notebook/deployment.py
deployml/notebook/display.py
deployml/notebook/stack.py
deployml/notebook/urls.py
deployml/notebook.py
deployml/templates/gcp/cloud_run/base_main.tf.j2
deployml/templates/gcp/cloud_run/main.tf.j2
deployml/templates/gcp/cloud_run/mlflow_main.tf.j2
deployml/templates/gcp/cloud_run/terraform.tfvars.j2
deployml/templates/gcp/cloud_run/variables.tf.j2
deployml/templates/gcp/cloud_run/wandb_main.tf.j2
deployml/templates/gcp/cloud_vm/main.tf.j2
deployml/templates/gcp/cloud_vm/terraform.tfvars.j2
deployml/templates/gcp/cloud_vm/variables.tf.j2
deployml/templates/kubernetes_local/deployment.yaml.j2
deployml/templates/kubernetes_local/mlflow-deployment.yaml.j2
deployml/templates/kubernetes_local/mlflow-service.yaml.j2
deployml/templates/kubernetes_local/service.yaml.j2
deployml/terraform/modules/cloud_sql_postgres/main.tf
deployml/terraform/modules/cloud_sql_postgres/outputs.tf
deployml/terraform/modules/cloud_sql_postgres/variables.tf
deployml/terraform/modules/cron/cloud/gcp/cloud_run/main.tf
deployml/terraform/modules/cron/cloud/gcp/cloud_run/outputs.tf
deployml/terraform/modules/cron/cloud/gcp/cloud_run/variables.tf
deployml/terraform/modules/explainability_monitoring/cloud/gcp/cloud_run/main.tf
deployml/terraform/modules/explainability_monitoring/cloud/gcp/cloud_run/outputs.tf
deployml/terraform/modules/explainability_monitoring/cloud/gcp/cloud_run/variables.tf
deployml/terraform/modules/fairness_monitoring/cloud/gcp/cloud_run/main.tf
deployml/terraform/modules/fairness_monitoring/cloud/gcp/cloud_run/outputs.tf
deployml/terraform/modules/fairness_monitoring/cloud/gcp/cloud_run/variables.tf
deployml/terraform/modules/fastapi/cloud/gcp/cloud_run/main.tf
deployml_core-0.0.51.dist-info/METADATA
deployml_core-0.0.51.dist-info/WHEEL
deployml_core-0.0.51.dist-info/entry_points.txt
deployml_core-0.0.51.dist-info/licenses/LICENSE
deployml_core-0.0.51.dist-info/RECORD
