Metadata-Version: 2.4
Name: deployml-core
Version: 0.0.51
Summary: Infra for academia
License-File: LICENSE
Author: Drew Hoang
Author-email: codentell@gmail.com
Requires-Python: >=3.11
Classifier: Programming Language :: Python :: 3
Classifier: Programming Language :: Python :: 3.11
Classifier: Programming Language :: Python :: 3.12
Classifier: Programming Language :: Python :: 3.13
Classifier: Programming Language :: Python :: 3.14
Requires-Dist: google-cloud-storage (>=3.1.1,<4.0.0)
Requires-Dist: ipython (>=9.0.0)
Requires-Dist: jinja2
Requires-Dist: jupyter (>=1.0.0)
Requires-Dist: pandas (>=2.2.1)
Requires-Dist: pyyaml
Requires-Dist: requests (>=2.28.0)
Requires-Dist: rich
Requires-Dist: typer
